{
  "issue": 905,
  "status": "running",
  "branch": "",
  "pr": null,
  "window": "",
  "started_at": "2026-04-23T06:07:42Z",
  "updated_at": "2026-04-23T06:08:32Z",
  "last_heartbeat_at": "2026-04-23T06:08:31Z",
  "current_step": "init",
  "retry_count": 0,
  "ac_verify_call_count": 0,
  "fix_instructions": null,
  "merged_at": null,
  "files_changed": [],
  "failure": null,
  "implementation_pr": null,
  "deltaspec_mode": null,
  "input_waiting_detected": null,
  "input_waiting_at": null,
  "is_quick": true,
  "is_direct": false,
  "mode": "direct"
}
